Workbook

Sheet Model
A1: DRiX Business-Impact Model — illustrative, assumption-based
A2: Layer 2 of the study. The simulation (Layer 1) measures only the QUALITY edge. The reply/win/cycle figures below are MODELED from published industry benchmarks (see Sources tab) and are estimates, not measured outcomes. Read 'Expected' as the headline; 'Conservative' is the safe floor.
A4: SIMULATION RESULTS (paste from benchmark_results.csv OVERALL rows after the run)
A5: DRiX blind win-rate vs GPT-4o | C5: 0 | F5: Headline credibility metric. From OVERALL/gpt4o row, drix_win_rate.
A6: DRiX relative score lift vs GPT-4o | C6: 0 | F6: From OVERALL/gpt4o row, rel_lift_pct (likelihood-to-respond).
A7: DRiX blind win-rate vs Flash-lite | C7: 0 | F7: From OVERALL/flashlite row, drix_win_rate.
A8: DRiX relative score lift vs Flash-lite | C8: 0 | F8: From OVERALL/flashlite row, rel_lift_pct.
A9: Note: the model below anchors DRiX's reply-rate lift to PUBLISHED personalization research, cross-checked for direction against the simulation above (a higher win-rate supports the upper bands).
A11: ASSUMPTIONS (blue = edit these)
A12: Scenario | B12: Conservative | C12: Expected | D12: Optimistic | F12: Source (see Sources tab)
A13: Baseline cold-email reply rate | B13: 0.03 | C13: 0.04 | D13: 0.05 | F13: B2B avg ~3-5% (Belkins, Instantly, Built For B2B, 2025).
A14: DRiX reply-rate multiplier (personalization lift) | B14: 1.32 | C14: 2 | D14: 4 | F14: Personalization lift: +32.7% (SalesS.io) -> ~2x advanced (9%->18%) -> 4-8x extreme (Martal/Apollo).
A15: Reply -> closed-won conversion | B15: 0.05 | C15: 0.1 | D15: 0.15 | F15: Composite of funnel benchmarks: SQL->opp ~50%, opp->close 15-40%, meeting->close ~33% (Glue Up, HiBob).
A16: Baseline sales-cycle length (days) | B16: 84 | C16: 84 | D16: 84 | F16: B2B SaaS median ~84 days (Optifai, 2025).
A17: DRiX sales-cycle reduction | B17: 0.1 | C17: 0.25 | D17: 0.45 | F17: Personalization/relevance -> 40-50% reduction at high end (treated as ceiling); Expected ~half.
A18: Leads contacted (basis for win counts) | B18: 1000 | C18: 1000 | D18: 1000 | F18: Arbitrary basis for expressing absolute wins; change freely.
A20: METRIC 1 — COLD-EMAIL RESPONSE RATE
A21: Baseline response rate | B21: =B13 -> 0.03 | C21: =C13 -> 0.04 | D21: =D13 -> 0.05
A22: DRiX response rate | B22: =B13*B14 -> 0.0396 | C22: =C13*C14 -> 0.08 | D22: =D13*D14 -> 0.2
A23: Response-rate lift | B23: =B22/B21-1 -> 0.32 | C23: =C22/C21-1 -> 1 | D23: =D22/D21-1 -> 3
A25: METRIC 2 — WIN RATE (per leads-contacted basis, downstream conversion held equal)
A26: Baseline closed-won deals | B26: =B18*B13*B15 -> 1.5 | C26: =C18*C13*C15 -> 4 | D26: =D18*D13*D15 -> 7.5
A27: DRiX closed-won deals | B27: =B18*(B13*B14)*B15 -> 1.98 | C27: =C18*(C13*C14)*C15 -> 8 | D27: =D18*(D13*D14)*D15 -> 30
A28: Additional wins vs baseline | B28: =B27-B26 -> 0.48 | C28: =C27-C26 -> 4 | D28: =D27-D26 -> 22.5
A29: Win-rate lift | B29: =B27/B26-1 -> 0.32 | C29: =C27/C26-1 -> 1 | D29: =D27/D26-1 -> 3
A31: METRIC 3 — SALES-CYCLE LENGTH
A32: Baseline cycle (days) | B32: =B16 -> 84 | C32: =C16 -> 84 | D32: =D16 -> 84
A33: DRiX cycle (days) | B33: =B16*(1-B17) -> 75.6 | C33: =C16*(1-C17) -> 63 | D33: =D16*(1-D17) -> 46.2
A34: Days saved | B34: =B32-B33 -> 8.4 | C34: =C32-C33 -> 21 | D34: =D32-D33 -> 37.8
A35: Cycle reduction | B35: =B17 -> 0.1 | C35: =C17 -> 0.25 | D35: =D17 -> 0.45
A37: HONEST FRAMING: lead with 'Expected'. These are AI-/benchmark-inferred estimates, not measured. A real pilot is the only way to confirm them.

Sheet ROI
A1: Customer ROI — what a $5,000/year DRiX subscription returns
A3: INPUTS (edit these — blue/yellow)
A4: DRiX subscription price ($/year) | B4: 5000 | F4: The annual fee the customer pays.
A5: Leads contacted per year | B5: 2000 | F5: How many prospects the customer emails in a year. EDIT to their volume.
A6: Average deal value / ACV ($) | B6: 15000 | F6: Revenue per closed deal. EDIT to their segment (SMB ~5k, mid ~15k, ent 100k+).
A7: Gross margin on new revenue (%) | B7: 1 | F7: Set <100% to count margin instead of top-line revenue.
A9: Scenario | B9: Conservative | C9: Expected | D9: Optimistic | F9: Pulls reply rate, lift multiplier & conversion from the Model tab
A10: Baseline deals won / year | B10: =$B$5*Model!B13*Model!B15 -> 3 | C10: =$B$5*Model!C13*Model!C15 -> 8 | D10: =$B$5*Model!D13*Model!D15 -> 15 | F10: leads x baseline reply rate x reply-to-won
A11: DRiX deals won / year | B11: =$B$5*(Model!B13*Model!B14)*Model!B15 -> 3.96 | C11: =$B$5*(Model!C13*Model!C14)*Model!C15 -> 16 | D11: =$B$5*(Model!D13*Model!D14)*Model!D15 -> 60 | F11: leads x (baseline reply x DRiX multiplier) x reply-to-won
A12: Additional deals / year (DRiX - baseline) | B12: =B11-B10 -> 0.96 | C12: =C11-C10 -> 8 | D12: =D11-D10 -> 45
A13: Additional revenue / year ($) | B13: =B12*$B$6*$B$7 -> 14400 | C13: =C12*$B$6*$B$7 -> 120000 | D13: =D12*$B$6*$B$7 -> 675000
A14: DRiX cost / year ($) | B14: =$B$4 -> 5000 | C14: =$B$4 -> 5000 | D14: =$B$4 -> 5000
A15: Net gain / year ($) | B15: =B13-B14 -> 9400 | C15: =C13-C14 -> 115000 | D15: =D13-D14 -> 670000
A16: ROI (revenue / cost) | B16: =B13/B14 -> 2.88 | C16: =C13/C14 -> 24 | D16: =D13/D14 -> 135
A17: ROI (%) | B17: =B15/B14 -> 1.88 | C17: =C15/C14 -> 23 | D17: =D15/D14 -> 134
A18: Break-even: extra deals needed to cover fee | B18: =$B$4/$B$6 -> 0.33333333 | C18: =$B$4/$B$6 -> 0.33333333 | D18: =$B$4/$B$6 -> 0.33333333
A19: Clears break-even? | B19: =IF(B12>=B18,"YES","no") -> YES | C19: =IF(C12>=C18,"YES","no") -> YES | D19: =IF(D12>=D18,"YES","no") -> YES
A21: These ROI figures are MODELED from the assumption bands on the Model tab and the inputs above. They are estimates, not guaranteed returns. Lead with 'Expected'; quote 'Conservative' as the floor. A live pilot is the only way to confirm them.

Sheet Sources
A1: Sources & Benchmarks
A2: Metric | B2: Figure used | C2: Source
A3: Cold-email reply rate (baseline) | B3: ~3-5% B2B avg (2025) | C3: Belkins — belkins.io/blog/cold-email-response-rates
A4: Cold-email reply rate (baseline) | B4: ~3.4-5.1% platform avg | C4: Built For B2B — builtforb2b.com/blog/b2b-cold-email-benchmark-2025
A5: Personalization reply lift | B5: +32.7% personalized content | C5: SalesS.io (via cold email statistics roundups)
A6: Personalization reply lift | B6: ~2x: 9% -> 18% advanced personalization | C6: thedigitalbloom.com/learn/cold-outbound-reply-rate-benchmarks
A7: Personalization reply lift | B7: +142% / up to 4-8x | C7: Martal — martal.ca/b2b-cold-email-statistics-lb; Apollo.io insights
A8: Funnel: SQL->opportunity | B8: ~50% (high performers 55-62%) | C8: Glue Up — glueup.com/blog/sales-funnel-conversion-rate-benchmarks
A9: Funnel: opportunity->close | B9: ~15-40% (SMB ~39%, Ent ~31%) | C9: Glue Up; HiBob — hibob.com/blog/sales-funnel-conversion-rate
A10: Funnel: meeting->close | B10: ~33% | C10: HiBob / industry benchmark roundups
A11: Baseline sales-cycle length | B11: ~84 days B2B SaaS median | C11: Optifai — optif.ai/learn/questions/sales-cycle-length-benchmark
A12: Sales-cycle reduction (personalization) | B12: 40-50% at high end | C12: Personalization velocity studies (treated as ceiling)
A14: Note: figures are public vendor/industry benchmarks, not peer-reviewed. Ranges are wide on purpose; the model uses them as Conservative/Expected/Optimistic bands rather than point claims.
